README.md
package_info.json
setup.py
th2_grpc_lw_data_provider/__init__.py
th2_grpc_lw_data_provider/lw_data_provider.proto
th2_grpc_lw_data_provider/lw_data_provider_pb2.py
th2_grpc_lw_data_provider/lw_data_provider_pb2.pyi
th2_grpc_lw_data_provider/lw_data_provider_pb2_grpc.py
th2_grpc_lw_data_provider/py.typed
th2_grpc_lw_data_provider/queue_data_provider.proto
th2_grpc_lw_data_provider/queue_data_provider_pb2.py
th2_grpc_lw_data_provider/queue_data_provider_pb2.pyi
th2_grpc_lw_data_provider/queue_data_provider_pb2_grpc.py
th2_grpc_lw_data_provider.egg-info/PKG-INFO
th2_grpc_lw_data_provider.egg-info/SOURCES.txt
th2_grpc_lw_data_provider.egg-info/dependency_links.txt
th2_grpc_lw_data_provider.egg-info/requires.txt
th2_grpc_lw_data_provider.egg-info/top_level.txt