Metadata-Version: 2.4
Name: th2_grpc_lw_data_provider
Version: 2.6.0.dev20453408317
Summary: th2_grpc_lw_data_provider
Home-page: https://github.com/th2-net/th2-lw-data-provider/grpc
Author: TH2-devs
Author-email: th2-devs@exactprosystems.com
License: Apache License 2.0
Requires-Python: >=3.7
Requires-Dist: th2-grpc-common<5,>=4.7.2
Dynamic: author
Dynamic: author-email
Dynamic: description
Dynamic: description-content-type
Dynamic: home-page
Dynamic: license
Dynamic: requires-dist
Dynamic: requires-python
Dynamic: summary
